{
  "$schema": "https://ui.shadcn.com/schema/registry-item.json",
  "name": "theme",
  "type": "registry:theme",
  "title": "Nature Theme",
  "description": "A nature theme and styles with greens and browns using Tailwind and shadcn/ui variable names",
  "dependencies": [
    "radix-ui"
  ],
  "files": [
    {
      "path": "src/app/globals.css",
      "content": "@import \"tailwindcss\";\n@import \"tw-animate-css\";\n\n@custom-variant dark (&:is(.dark *));\n\n:root {\n  /* Semantic tokens map to Catlife by default */\n  --background: var(--catlife-background);\n  --foreground: var(--catlife-text-primary);\n\n  --card: var(--catlife-surface);\n  --card-foreground: var(--catlife-text-primary);\n\n  --popover: var(--catlife-surface);\n  --popover-foreground: var(--catlife-text-primary);\n\n  --primary: var(--catlife-primary);\n  --primary-foreground: var(--catlife-text-inverse);\n\n  --secondary: var(--catlife-primary-light);\n  --secondary-foreground: var(--catlife-text-primary);\n\n  --muted: var(--catlife-background-alt);\n  --muted-foreground: var(--catlife-text-muted);\n\n  --accent: var(--catlife-primary-light);\n  --accent-foreground: var(--catlife-text-primary);\n\n  --destructive: #ef4444;\n  --destructive-foreground: #ffffff;\n\n  --border: var(--catlife-border);\n  --input: var(--catlife-border);\n  --ring: var(--catlife-primary);\n\n  /* Keep charts and sidebar as-is for now; can be themed later */\n  --chart-1: oklch(0.67 0.16 144.21);\n  --chart-2: oklch(0.58 0.14 144.18);\n  --chart-3: oklch(0.52 0.13 144.17);\n  --chart-4: oklch(0.43 0.12 144.31);\n  --chart-5: oklch(0.22 0.05 145.73);\n\n  --sidebar: oklch(0.94 0.01 74.42);\n  --sidebar-foreground: oklch(0.3 0.04 30.2);\n  --sidebar-primary: oklch(0.52 0.13 144.17);\n  --sidebar-primary-foreground: oklch(1.0 0 0);\n  --sidebar-accent: oklch(0.9 0.05 146.04);\n  --sidebar-accent-foreground: oklch(0.43 0.12 144.31);\n  --sidebar-border: oklch(0.88 0.02 74.64);\n  --sidebar-ring: oklch(0.52 0.13 144.17);\n\n  --radius: var(--catlife-radius);\n\n  /* Adding Catlife custom colors while preserving shadcn/ui defaults */\n\n  /* Catlife Primary Colors - Orange Family */\n  --catlife-primary: #f49834;\n  --catlife-primary-hover: #f99830;\n  --catlife-primary-active: #f27100;\n  --catlife-primary-light: #ffd094;\n  --catlife-primary-lightest: #ffeed6;\n\n  /* Catlife Background Colors */\n  --catlife-background: #fffaf4;\n  --catlife-background-alt: #fffaf3;\n  --catlife-surface: #ffffff;\n\n  /* Catlife Text Colors */\n  --catlife-text-primary: #161616;\n  --catlife-text-secondary: #1c1b1f;\n  --catlife-text-muted: #292625;\n  --catlife-text-inverse: #ffffff;\n  --catlife-text-variant-1: #151515;\n  --catlife-text-variant-2: #161617;\n\n  /* Catlife Accent Colors */\n  --catlife-accent-success: #10b981;\n\n  /* Catlife Border */\n  --catlife-border: #161616;\n  --catlife-radius: 1.5rem;\n\n  /* Added Catlife font token */\n  --catlife-font-primary: \"Roc Grotesk\", -apple-system, BlinkMacSystemFont, \"Segoe UI\", Roboto, sans-serif;\n}\n\n.dark {\n  --background: var(--catlife-background);\n  --foreground: var(--catlife-text-primary);\n\n  --card: var(--catlife-surface);\n  --card-foreground: var(--catlife-text-primary);\n\n  --popover: var(--catlife-surface);\n  --popover-foreground: var(--catlife-text-primary);\n\n  --primary: var(--catlife-primary);\n  --primary-foreground: var(--catlife-text-inverse);\n\n  --secondary: var(--catlife-primary-light);\n  --secondary-foreground: var(--catlife-text-primary);\n\n  --muted: var(--catlife-background-alt);\n  --muted-foreground: var(--catlife-text-muted);\n\n  --accent: var(--catlife-primary-light);\n  --accent-foreground: var(--catlife-text-primary);\n\n  --destructive: #ef4444;\n  --destructive-foreground: #ffffff;\n\n  --border: var(--catlife-border);\n  --input: var(--catlife-border);\n  --ring: var(--catlife-primary);\n\n  /* Keep chart/sidebar dark defaults */\n  --chart-1: oklch(0.72 0.16 144.21);\n  --chart-2: oklch(0.63 0.14 144.18);\n  --chart-3: oklch(0.58 0.15 144.17);\n  --chart-4: oklch(0.48 0.12 144.31);\n  --chart-5: oklch(0.35 0.08 145.73);\n\n  --sidebar: oklch(0.15 0.01 74.42);\n  --sidebar-foreground: oklch(0.95 0.02 80.72);\n  --sidebar-primary: oklch(0.58 0.15 144.17);\n  --sidebar-primary-foreground: oklch(0.09 0.01 80.72);\n  --sidebar-accent: oklch(0.22 0.04 146.04);\n  --sidebar-accent-foreground: oklch(0.65 0.12 144.31);\n  --sidebar-border: oklch(0.22 0.02 74.64);\n  --sidebar-ring: oklch(0.58 0.15 144.17);\n}\n\n/* Named themes for consumers */\n.theme-catlife,\n.catlife-theme {\n  --background: var(--catlife-background);\n  --foreground: var(--catlife-text-primary);\n  --card: var(--catlife-surface);\n  --card-foreground: var(--catlife-text-primary);\n  --popover: var(--catlife-surface);\n  --popover-foreground: var(--catlife-text-primary);\n\n  --primary: var(--catlife-primary);\n  --primary-foreground: var(--catlife-text-inverse);\n\n  --secondary: var(--catlife-primary-light);\n  --secondary-foreground: var(--catlife-text-primary);\n\n  --muted: var(--catlife-background-alt);\n  --muted-foreground: var(--catlife-text-muted);\n\n  --accent: var(--catlife-primary-light);\n  --accent-foreground: var(--catlife-text-primary);\n\n  --destructive: #ef4444;\n  --destructive-foreground: #ffffff;\n\n  --border: var(--catlife-border);\n  --input: var(--catlife-border);\n  --ring: var(--catlife-primary);\n\n  --radius: var(--catlife-radius);\n\n  font-family: var(--catlife-font-primary);\n}\n\n.theme-default {\n  /* Original shadcn defaults (light) */\n  --background: oklch(0.97 0.01 80.72);\n  --foreground: oklch(0.3 0.04 30.2);\n  --card: oklch(0.97 0.01 80.72);\n  --card-foreground: oklch(0.3 0.04 30.2);\n  --popover: oklch(0.97 0.01 80.72);\n  --popover-foreground: oklch(0.3 0.04 30.2);\n  --primary: oklch(0.52 0.13 144.17);\n  --primary-foreground: oklch(1.0 0 0);\n  --secondary: oklch(0.96 0.02 147.64);\n  --secondary-foreground: oklch(0.43 0.12 144.31);\n  --muted: oklch(0.94 0.01 74.42);\n  --muted-foreground: oklch(0.45 0.05 39.21);\n  --accent: oklch(0.9 0.05 146.04);\n  --accent-foreground: oklch(0.43 0.12 144.31);\n  --destructive: oklch(0.54 0.19 26.72);\n  --destructive-foreground: oklch(1.0 0 0);\n  --border: oklch(0.88 0.02 74.64);\n  --input: oklch(0.88 0.02 74.64);\n  --ring: oklch(0.52 0.13 144.17);\n}\n\n.dark.theme-default {\n  --background: oklch(0.15 0.01 74.42);\n  --foreground: oklch(0.95 0.02 80.72);\n  --card: oklch(0.12 0.01 80.72);\n  --card-foreground: oklch(0.95 0.02 80.72);\n  --popover: oklch(0.12 0.01 80.72);\n  --popover-foreground: oklch(0.95 0.02 80.72);\n  --primary: oklch(0.58 0.15 144.17);\n  --primary-foreground: oklch(0.09 0.01 80.72);\n  --secondary: oklch(0.15 0.02 147.64);\n  --secondary-foreground: oklch(0.65 0.12 144.31);\n  --muted: oklch(0.18 0.01 74.42);\n  --muted-foreground: oklch(0.65 0.03 74.42);\n  --accent: oklch(0.22 0.04 146.04);\n  --accent-foreground: oklch(0.65 0.12 144.31);\n  --destructive: oklch(0.62 0.22 26.72);\n  --destructive-foreground: oklch(0.95 0.02 80.72);\n  --border: oklch(0.22 0.02 74.64);\n  --input: oklch(0.22 0.02 74.64);\n  --ring: oklch(0.58 0.15 144.17);\n}\n\n@theme inline {\n  --color-background: var(--background);\n  --color-foreground: var(--foreground);\n\n  --color-primary: var(--primary);\n  --color-primary-foreground: var(--primary-foreground);\n\n  --color-secondary: var(--secondary);\n  --color-secondary-foreground: var(--secondary-foreground);\n  --color-accent: var(--accent);\n  --color-accent-foreground: var(--accent-foreground);\n\n  --color-muted: var(--muted);\n  --color-muted-foreground: var(--muted-foreground);\n  --color-card: var(--card);\n  --color-card-foreground: var(--card-foreground);\n  --color-popover: var(--popover);\n  --color-popover-foreground: var(--popover-foreground);\n\n  --color-border: var(--border);\n  --color-input: var(--input);\n  --color-ring: var(--ring);\n\n  --color-destructive: var(--destructive);\n  --color-destructive-foreground: var(--destructive-foreground);\n\n  --color-chart-1: var(--chart-1);\n  --color-chart-2: var(--chart-2);\n  --color-chart-3: var(--chart-3);\n  --color-chart-4: var(--chart-4);\n  --color-chart-5: var(--chart-5);\n\n  --color-sidebar: var(--sidebar);\n  --color-sidebar-foreground: var(--sidebar-foreground);\n  --color-sidebar-primary: var(--sidebar-primary);\n  --color-sidebar-primary-foreground: var(--sidebar-primary-foreground);\n  --color-sidebar-accent: var(--sidebar-accent);\n  --color-sidebar-accent-foreground: var(--sidebar-accent-foreground);\n  --color-sidebar-border: var(--sidebar-border);\n  --color-sidebar-ring: var(--sidebar-ring);\n\n  /* Catlife color tokens */\n  --color-catlife-primary: var(--catlife-primary);\n  --color-catlife-primary-hover: var(--catlife-primary-hover);\n  --color-catlife-primary-active: var(--catlife-primary-active);\n  --color-catlife-primary-light: var(--catlife-primary-light);\n  --color-catlife-primary-lightest: var(--catlife-primary-lightest);\n  --color-catlife-background: var(--catlife-background);\n  --color-catlife-background-alt: var(--catlife-background-alt);\n  --color-catlife-surface: var(--catlife-surface);\n  --color-catlife-text-primary: var(--catlife-text-primary);\n  --color-catlife-text-secondary: var(--catlife-text-secondary);\n  --color-catlife-text-muted: var(--catlife-text-muted);\n  --color-catlife-text-inverse: var(--catlife-text-inverse);\n  --color-catlife-text-variant-1: var(--catlife-text-variant-1);\n  --color-catlife-text-variant-2: var(--catlife-text-variant-2);\n  --color-catlife-accent-success: var(--catlife-accent-success);\n  --color-catlife-border: var(--catlife-border);\n\n  --font-sans: var(--font-sans);\n  --font-serif: var(--font-serif);\n  --font-mono: var(--font-mono);\n  --font-catlife-primary: var(--catlife-font-primary);\n\n  --radius-sm: calc(var(--radius) - 4px);\n  --radius-md: calc(var(--radius) - 2px);\n  --radius-lg: var(--radius);\n  --radius-xl: calc(var(--radius) + 4px);\n  --radius-catlife: var(--catlife-radius);\n\n  --shadow-2xs: var(--shadow-2xs);\n  --shadow-xs: var(--shadow-xs);\n  --shadow-sm: var(--shadow-sm);\n  --shadow: var(--shadow);\n  --shadow-md: var(--shadow-md);\n  --shadow-lg: var(--shadow-lg);\n  --shadow-xl: var(--shadow-xl);\n  --shadow-2xl: var(--shadow-2xl);\n}\n\n@layer base {\n  *,\n  ::after,\n  ::before,\n  ::backdrop,\n  ::file-selector-button {\n    border-color: var(--color-border, currentColor);\n  }\n}\n",
      "type": "registry:style",
      "target": "app/globals.css"
    },
    {
      "path": "postcss.config.mjs",
      "content": "/** @type {import('postcss-load-config').Config} */\nexport default {\n  plugins: {\n    \"@tailwindcss/postcss\": {},\n  },\n};\n",
      "type": "registry:file",
      "target": "postcss.config.mjs"
    }
  ],
  "cssVars": {
    "light": {
      "background": "oklch(0.97 0.01 80.72)",
      "foreground": "oklch(0.3 0.04 30.2)",
      "card": "oklch(0.97 0.01 80.72)",
      "card-foreground": "oklch(0.3 0.04 30.2)",
      "popover": "oklch(0.97 0.01 80.72)",
      "popover-foreground": "oklch(0.3 0.04 30.2)",
      "primary": "oklch(0.52 0.13 144.17)",
      "primary-foreground": "oklch(1.0 0 0)",
      "secondary": "oklch(0.96 0.02 147.64)",
      "secondary-foreground": "oklch(0.43 0.12 144.31)",
      "muted": "oklch(0.94 0.01 74.42)",
      "muted-foreground": "oklch(0.45 0.05 39.21)",
      "accent": "oklch(0.9 0.05 146.04)",
      "accent-foreground": "oklch(0.43 0.12 144.31)",
      "destructive": "oklch(0.54 0.19 26.72)",
      "destructive-foreground": "oklch(1.0 0 0)",
      "border": "oklch(0.88 0.02 74.64)",
      "input": "oklch(0.88 0.02 74.64)",
      "ring": "oklch(0.52 0.13 144.17)",
      "chart-1": "oklch(0.67 0.16 144.21)",
      "chart-2": "oklch(0.58 0.14 144.18)",
      "chart-3": "oklch(0.52 0.13 144.17)",
      "chart-4": "oklch(0.43 0.12 144.31)",
      "chart-5": "oklch(0.22 0.05 145.73)",
      "sidebar": "oklch(0.94 0.01 74.42)",
      "sidebar-foreground": "oklch(0.3 0.04 30.2)",
      "sidebar-primary": "oklch(0.52 0.13 144.17)",
      "sidebar-primary-foreground": "oklch(1.0 0 0)",
      "sidebar-accent": "oklch(0.9 0.05 146.04)",
      "sidebar-accent-foreground": "oklch(0.43 0.12 144.31)",
      "sidebar-border": "oklch(0.88 0.02 74.64)",
      "sidebar-ring": "oklch(0.52 0.13 144.17)",
      "radius": "0.5rem"
    },
    "dark": {
      "background": "oklch(0.15 0.01 74.42)",
      "foreground": "oklch(0.95 0.02 80.72)",
      "card": "oklch(0.12 0.01 80.72)",
      "card-foreground": "oklch(0.95 0.02 80.72)",
      "popover": "oklch(0.12 0.01 80.72)",
      "popover-foreground": "oklch(0.95 0.02 80.72)",
      "primary": "oklch(0.58 0.15 144.17)",
      "primary-foreground": "oklch(0.09 0.01 80.72)",
      "secondary": "oklch(0.15 0.02 147.64)",
      "secondary-foreground": "oklch(0.65 0.12 144.31)",
      "muted": "oklch(0.18 0.01 74.42)",
      "muted-foreground": "oklch(0.65 0.03 74.42)",
      "accent": "oklch(0.22 0.04 146.04)",
      "accent-foreground": "oklch(0.65 0.12 144.31)",
      "destructive": "oklch(0.62 0.22 26.72)",
      "destructive-foreground": "oklch(0.95 0.02 80.72)",
      "border": "oklch(0.22 0.02 74.64)",
      "input": "oklch(0.22 0.02 74.64)",
      "ring": "oklch(0.58 0.15 144.17)",
      "chart-1": "oklch(0.72 0.16 144.21)",
      "chart-2": "oklch(0.63 0.14 144.18)",
      "chart-3": "oklch(0.58 0.15 144.17)",
      "chart-4": "oklch(0.48 0.12 144.31)",
      "chart-5": "oklch(0.35 0.08 145.73)",
      "sidebar": "oklch(0.15 0.01 74.42)",
      "sidebar-foreground": "oklch(0.95 0.02 80.72)",
      "sidebar-primary": "oklch(0.58 0.15 144.17)",
      "sidebar-primary-foreground": "oklch(0.09 0.01 80.72)",
      "sidebar-accent": "oklch(0.22 0.04 146.04)",
      "sidebar-accent-foreground": "oklch(0.65 0.12 144.31)",
      "sidebar-border": "oklch(0.22 0.02 74.64)",
      "sidebar-ring": "oklch(0.58 0.15 144.17)",
      "radius": "0.5rem"
    }
  }
}